tracking_mcp/__init__.py
tracking_mcp/tracking_server.py
tracking_mcp-1.0.1.dist-info/licenses/LICENSE
tracking_mcp-1.0.1.dist-info/METADATA
tracking_mcp-1.0.1.dist-info/WHEEL
tracking_mcp-1.0.1.dist-info/entry_points.txt
tracking_mcp-1.0.1.dist-info/top_level.txt
tracking_mcp-1.0.1.dist-info/RECORD
