Metadata-Version: 2.4
Name: tracking-mcp
Version: 1.0.1
Summary: MCP server for generic entity tracking with JSON Hybrid storage
Author: Mario Mosca
License: MIT
Requires-Python: >=3.10
License-File: LICENSE
Requires-Dist: mcp>=1.7.1
Requires-Dist: aiosqlite>=0.19.0
Requires-Dist: python-dateutil>=2.8.0
Provides-Extra: dev
Requires-Dist: pytest>=7.4.0; extra == "dev"
Requires-Dist: pytest-asyncio>=0.21.0; extra == "dev"
Requires-Dist: black>=23.0.0; extra == "dev"
Requires-Dist: ruff>=0.1.0; extra == "dev"
Dynamic: license-file
